chrompy/__init__.py
chrompy-0.0.1.dist-info/LICENSE
chrompy-0.0.1.dist-info/METADATA
chrompy-0.0.1.dist-info/WHEEL
chrompy-0.0.1.dist-info/top_level.txt
chrompy-0.0.1.dist-info/RECORD
