Metadata-Version: 2.1
Name: chrompy
Version: 0.0.1
Summary: Chrome driver fully automated
Home-page: https://github.com/Platob/Chrompy.git
Author: Fillot Nicolas
Author-email: nfillot.pro@gmail.com
License: Apache License 2.0
License-File: LICENSE
